FileManager.dll
Localization.dll
Log.dll
sqlite3.dll
web_framework_api.cp314-win_amd64.pyd
web_framework_api.pyi
WebFramework.dll
web_framework_api-3.2.0.dist-info/METADATA
web_framework_api-3.2.0.dist-info/WHEEL
web_framework_api-3.2.0.dist-info/licenses/license/LICENSE
web_framework_api-3.2.0.dist-info/RECORD
