Metadata-Version: 2.2
Name: web_framework_api
Version: 3.2.0
Summary: Python API for WebFramework
Keywords: Web
Author-Email: LazyPanda07 <semengricenko@gmail.com>
Maintainer-Email: LazyPanda07 <semengricenko@gmail.com>
License: MIT License
Classifier: Programming Language :: Python :: 3.14
Classifier: License :: OSI Approved :: MIT License
Classifier: Operating System :: Microsoft :: Windows
Classifier: Operating System :: POSIX :: Linux
Project-URL: Repository, http://github.com/LazyPanda07/WebFramework
Project-URL: Wiki, http://github.com/LazyPanda07/WebFramework/wiki
Requires-Python: ==3.14.*
